bind_chain_app_client/__init__.py
bind_chain_app_client/api_client.py
bind_chain_app_client/api_response.py
bind_chain_app_client/configuration.py
bind_chain_app_client/exceptions.py
bind_chain_app_client/py.typed
bind_chain_app_client/rest.py
bind_chain_app_client/api/__init__.py
bind_chain_app_client/api/auth_api.py
bind_chain_app_client/api/main_api.py
bind_chain_app_client/api/main_pool_api.py
bind_chain_app_client/api/mass_claiming_api.py
bind_chain_app_client/api/user_info_api.py
bind_chain_app_client/models/__init__.py
bind_chain_app_client/models/get_claimable_bind_data_response.py
bind_chain_app_client/models/get_claimable_bind_item_response.py
bind_chain_app_client/models/get_claimable_bind_response.py
bind_chain_app_client/models/get_release_date_by_user.py
bind_chain_app_client/models/get_release_date_by_user_data.py
bind_chain_app_client/models/locked_bind.py
bind_chain_app_client/models/main_pool_info.py
bind_chain_app_client/models/main_pool_info_data.py
bind_chain_app_client/models/mass_claiming.py
bind_chain_app_client/models/mass_claiming_response.py
bind_chain_app_client/models/pool_size_history.py
bind_chain_app_client/models/pool_size_history_item.py
bind_chain_app_client/models/sign_in_user.py
bind_chain_app_client/models/sign_up_user.py
bind_chain_app_client/models/stake.py
bind_chain_app_client/models/stake_data_response.py
bind_chain_app_client/models/stake_response.py
bind_chain_app_client/models/staked_bind.py
bind_chain_app_client/models/staked_bind_data.py
bind_chain_app_client/models/unstakable_bind.py
bind_chain_app_client/models/unstakable_bind_data.py
bind_chain_app_client/models/unstake.py
bind_chain_app_client/models/unstake_data_response.py
bind_chain_app_client/models/unstake_response.py
bind_chain_app_client/models/user_data_response.py
bind_chain_app_client/models/user_response.py
openapi_client/__init__.py
openapi_client/api_client.py
openapi_client/configuration.py
openapi_client/exceptions.py
openapi_client/rest.py
bind_chain_app_client-1.0.2.dist-info/METADATA
bind_chain_app_client-1.0.2.dist-info/WHEEL
bind_chain_app_client-1.0.2.dist-info/top_level.txt
bind_chain_app_client-1.0.2.dist-info/RECORD
