Metadata-Version: 2.1
Name: bind-chain-app-client
Version: 1.0.2
Summary: Chain App BIND client SDK
Home-page: 
Author: BIND Contact
Author-email: support@bind.com
License: MIT
Keywords: OpenAPI,OpenAPI-Generator,Chain App BIND client SDK
Requires-Dist: urllib3 <2.1.0,>=1.25.3
Requires-Dist: python-dateutil
Requires-Dist: pydantic <2,>=1.10.5
Requires-Dist: aenum
